reqninja/__init__.py
reqninja/__main__.py
reqninja/_version.py
reqninja/auth.py
reqninja/cli.py
reqninja/client.py
reqninja/config.py
reqninja/exceptions.py
reqninja/response.py
reqninja/utils.py
reqninja-1.2.0.dist-info/licenses/LICENSE
reqninja-1.2.0.dist-info/METADATA
reqninja-1.2.0.dist-info/WHEEL
reqninja-1.2.0.dist-info/entry_points.txt
reqninja-1.2.0.dist-info/top_level.txt
reqninja-1.2.0.dist-info/RECORD
