Metadata-Version: 2.4
Name: reqninja
Version: 1.2.0
Summary: ReqNinja - A Python package and CLI tool for API testing, automation, and debugging
Author-email: vishal-ravi <dev.vishalravi@gmail.com>
License-Expression: MIT
Project-URL: Homepage, https://github.com/vishal-ravi/reqninja
Project-URL: Documentation, https://reqninja.readthedocs.io
Project-URL: Repository, https://github.com/vishal-ravi/reqninja.git
Project-URL: Issues, https://github.com/vishal-ravi/reqninja/issues
Keywords: api,http,requests,testing,cli,automation,debugging,ninja,reqninja
Classifier: Development Status :: 5 - Production/Stable
Classifier: Intended Audience :: Developers
Classifier: Operating System :: OS Independent
Classifier: Programming Language :: Python :: 3
Classifier: Programming Language :: Python :: 3.8
Classifier: Programming Language :: Python :: 3.9
Classifier: Programming Language :: Python :: 3.10
Classifier: Programming Language :: Python :: 3.11
Classifier: Programming Language :: Python :: 3.12
Classifier: Topic :: Internet :: WWW/HTTP
Classifier: Topic :: Software Development :: Testing
Classifier: Topic :: System :: Networking
Requires-Python: >=3.8
License-File: LICENSE
Requires-Dist: requests>=2.25.0
Requires-Dist: click>=8.0.0
Requires-Dist: pyyaml>=6.0
Requires-Dist: rich>=12.0.0
Requires-Dist: urllib3>=1.26.0
Requires-Dist: colorama>=0.4.4
Requires-Dist: pygments>=2.10.0
Requires-Dist: tabulate>=0.9.0
Provides-Extra: dev
Requires-Dist: pytest>=7.0.0; extra == "dev"
Requires-Dist: pytest-cov>=4.0.0; extra == "dev"
Requires-Dist: pytest-mock>=3.10.0; extra == "dev"
Requires-Dist: black>=22.0.0; extra == "dev"
Requires-Dist: isort>=5.10.0; extra == "dev"
Requires-Dist: flake8>=5.0.0; extra == "dev"
Requires-Dist: mypy>=1.0.0; extra == "dev"
Requires-Dist: pre-commit>=2.20.0; extra == "dev"
Requires-Dist: twine>=4.0.0; extra == "dev"
Requires-Dist: build>=0.8.0; extra == "dev"
Provides-Extra: test
Requires-Dist: pytest>=7.0.0; extra == "test"
Requires-Dist: pytest-cov>=4.0.0; extra == "test"
Requires-Dist: pytest-mock>=3.10.0; extra == "test"
Requires-Dist: responses>=0.22.0; extra == "test"
Requires-Dist: httpx>=0.24.0; extra == "test"
Dynamic: license-file
